lab03/lab03/adders.v
`timescale 1ns / 1ps

module half_adder(
    input a,
    input b,
    output sum,
    output carry
);
    assign sum = a ^ b;
    assign carry = a & b;
endmodule

module full_adder(
    input a,
    input b,
    input cin,
    output sum,
    output cout
);
    assign sum = a ^ b ^ cin;
    assign cout = (a & b) | (a & cin) | (b & cin);
endmodule

module adder_4bit(
    input [3:0] a,
    input [3:0] b,
    input cin,
    output [3:0] sum,
    output cout
);
    wire c1;
    wire c2;
    wire c3;

    full_adder fa0 (.a(a[0]), .b(b[0]), .cin(cin), .sum(sum[0]), .cout(c1));
    full_adder fa1 (.a(a[1]), .b(b[1]), .cin(c1), .sum(sum[1]), .cout(c2));
    full_adder fa2 (.a(a[2]), .b(b[2]), .cin(c2), .sum(sum[2]), .cout(c3));
    full_adder fa3 (.a(a[3]), .b(b[3]), .cin(c3), .sum(sum[3]), .cout(cout));
endmodule

module adder_8bit(
    input [7:0] a,
    input [7:0] b,
    input cin,
    output [7:0] sum,
    output cout
);
    wire c1, c2, c3, c4, c5, c6, c7;

    full_adder fa0 (.a(a[0]), .b(b[0]), .cin(cin), .sum(sum[0]), .cout(c1));
    full_adder fa1 (.a(a[1]), .b(b[1]), .cin(c1),   .sum(sum[1]), .cout(c2));
    full_adder fa2 (.a(a[2]), .b(b[2]), .cin(c2),   .sum(sum[2]), .cout(c3));
    full_adder fa3 (.a(a[3]), .b(b[3]), .cin(c3),   .sum(sum[3]), .cout(c4));
    full_adder fa4 (.a(a[4]), .b(b[4]), .cin(c4),   .sum(sum[4]), .cout(c5));
    full_adder fa5 (.a(a[5]), .b(b[5]), .cin(c5),   .sum(sum[5]), .cout(c6));
    full_adder fa6 (.a(a[6]), .b(b[6]), .cin(c6),   .sum(sum[6]), .cout(c7));
    full_adder fa7 (.a(a[7]), .b(b[7]), .cin(c7),   .sum(sum[7]), .cout(cout));
endmodule

lab03/lab03/tb_adders.v
`timescale 1ns / 1ps

module tb_adders;
    reg a;
    reg b;
    reg cin;
    wire ha_sum;
    wire ha_carry;
    wire sum;
    wire cout;

    reg [3:0] a4;
    reg [3:0] b4;
    reg cin4;
    wire [3:0] sum4;
    wire cout4;

    reg [7:0] a8;
    reg [7:0] b8;
    reg cin8;
    wire [7:0] sum8;
    wire cout8;

    integer i;

    half_adder ha (.a(a), .b(b), .sum(ha_sum), .carry(ha_carry));
    full_adder fa (.a(a), .b(b), .cin(cin), .sum(sum), .cout(cout));
    adder_4bit add4 (.a(a4), .b(b4), .cin(cin4), .sum(sum4), .cout(cout4));
    adder_8bit add8 (.a(a8), .b(b8), .cin(cin8), .sum(sum8), .cout(cout8));

    initial begin
        $dumpfile("lab03_adders.vcd");
        $dumpvars(0, tb_adders);

        $display("Full adder truth table");
        $display("a b cin | sum cout");

        for (i = 0; i < 8; i = i + 1) begin
            {a, b, cin} = i[2:0];
            #10;
            $display("%b %b  %b  |  %b    %b", a, b, cin, sum, cout);
        end

        $display("");
        $display("4-bit adder checks");
        a4 = 4'd3;  b4 = 4'd5;  cin4 = 1'b0; #10;
        $display("%d + %d + %d = %d carry=%b", a4, b4, cin4, sum4, cout4);

        a4 = 4'd9;  b4 = 4'd7;  cin4 = 1'b0; #10;
        $display("%d + %d + %d = %d carry=%b", a4, b4, cin4, sum4, cout4);

        a4 = 4'd15; b4 = 4'd15; cin4 = 1'b1; #10;
        $display("%d + %d + %d = %d carry=%b", a4, b4, cin4, sum4, cout4);

        $display("");
        $display("8-bit adder checks");
        a8 = 8'd10;   b8 = 8'd20;   cin8 = 1'b0; #10;
        $display("%d + %d + %d = %d carry=%b", a8, b8, cin8, sum8, cout8);

        a8 = 8'd100;  b8 = 8'd55;   cin8 = 1'b0; #10;
        $display("%d + %d + %d = %d carry=%b", a8, b8, cin8, sum8, cout8);

        a8 = 8'd200;  b8 = 8'd150;  cin8 = 1'b0; #10;
        $display("%d + %d + %d = %d carry=%b", a8, b8, cin8, sum8, cout8);

        a8 = 8'd255;  b8 = 8'd255;  cin8 = 1'b1; #10;
        $display("%d + %d + %d = %d carry=%b", a8, b8, cin8, sum8, cout8);

        $finish;
    end
endmodule

lab03/lab03/lab03_adders.vcd
$date
	Tue Jul 07 12:12:51 2026
$end
$version
	Icarus Verilog
$end
$timescale
	1ps
$end
$scope module tb_adders $end
$var wire 8 ! sum8 [7:0] $end
$var wire 4 " sum4 [3:0] $end
$var wire 1 # sum $end
$var wire 1 $ ha_sum $end
$var wire 1 % ha_carry $end
$var wire 1 & cout8 $end
$var wire 1 ' cout4 $end
$var wire 1 ( cout $end
$var reg 1 ) a $end
$var reg 4 * a4 [3:0] $end
$var reg 8 + a8 [7:0] $end
$var reg 1 , b $end
$var reg 4 - b4 [3:0] $end
$var reg 8 . b8 [7:0] $end
$var reg 1 / cin $end
$var reg 1 0 cin4 $end
$var reg 1 1 cin8 $end
$var integer 32 2 i [31:0] $end
$scope module add4 $end
$var wire 4 3 a [3:0] $end
$var wire 4 4 b [3:0] $end
$var wire 1 0 cin $end
$var wire 4 5 sum [3:0] $end
$var wire 1 ' cout $end
$var wire 1 6 c3 $end
$var wire 1 7 c2 $end
$var wire 1 8 c1 $end
$scope module fa0 $end
$var wire 1 9 a $end
$var wire 1 : b $end
$var wire 1 0 cin $end
$var wire 1 8 cout $end
$var wire 1 ; sum $end
$upscope $end
$scope module fa1 $end
$var wire 1 < a $end
$var wire 1 = b $end
$var wire 1 8 cin $end
$var wire 1 7 cout $end
$var wire 1 > sum $end
$upscope $end
$scope module fa2 $end
$var wire 1 ? a $end
$var wire 1 @ b $end
$var wire 1 7 cin $end
$var wire 1 6 cout $end
$var wire 1 A sum $end
$upscope $end
$scope module fa3 $end
$var wire 1 B a $end
$var wire 1 C b $end
$var wire 1 6 cin $end
$var wire 1 ' cout $end
$var wire 1 D sum $end
$upscope $end
$upscope $end
$scope module add8 $end
$var wire 8 E a [7:0] $end
$var wire 8 F b [7:0] $end
$var wire 1 1 cin $end
$var wire 8 G sum [7:0] $end
$var wire 1 & cout $end
$var wire 1 H c7 $end
$var wire 1 I c6 $end
$var wire 1 J c5 $end
$var wire 1 K c4 $end
$var wire 1 L c3 $end
$var wire 1 M c2 $end
$var wire 1 N c1 $end
$scope module fa0 $end
$var wire 1 O a $end
$var wire 1 P b $end
$var wire 1 1 cin $end
$var wire 1 N cout $end
$var wire 1 Q sum $end
$upscope $end
$scope module fa1 $end
$var wire 1 R a $end
$var wire 1 S b $end
$var wire 1 N cin $end
$var wire 1 M cout $end
$var wire 1 T sum $end
$upscope $end
$scope module fa2 $end
$var wire 1 U a $end
$var wire 1 V b $end
$var wire 1 M cin $end
$var wire 1 L cout $end
$var wire 1 W sum $end
$upscope $end
$scope module fa3 $end
$var wire 1 X a $end
$var wire 1 Y b $end
$var wire 1 L cin $end
$var wire 1 K cout $end
$var wire 1 Z sum $end
$upscope $end
$scope module fa4 $end
$var wire 1 [ a $end
$var wire 1 \ b $end
$var wire 1 K cin $end
$var wire 1 J cout $end
$var wire 1 ] sum $end
$upscope $end
$scope module fa5 $end
$var wire 1 ^ a $end
$var wire 1 _ b $end
$var wire 1 J cin $end
$var wire 1 I cout $end
$var wire 1 ` sum $end
$upscope $end
$scope module fa6 $end
$var wire 1 a a $end
$var wire 1 b b $end
$var wire 1 I cin $end
$var wire 1 H cout $end
$var wire 1 c sum $end
$upscope $end
$scope module fa7 $end
$var wire 1 d a $end
$var wire 1 e b $end
$var wire 1 H cin $end
$var wire 1 & cout $end
$var wire 1 f sum $end
$upscope $end
$upscope $end
$scope module fa $end
$var wire 1 ) a $end
$var wire 1 , b $end
$var wire 1 / cin $end
$var wire 1 ( cout $end
$var wire 1 # sum $end
$upscope $end
$scope module ha $end
$var wire 1 ) a $end
$var wire 1 , b $end
$var wire 1 % carry $end
$var wire 1 $ sum $end
$upscope $end
$upscope $end
$enddefinitions $end
$comment Show the parameter values. $end
$dumpall
$end
#0
$dumpvars
xf
xe
xd
xc
xb
xa
x`
x_
x^
x]
x\
x[
xZ
xY
xX
xW
xV
xU
xT
xS
xR
xQ
xP
xO
xN
xM
xL
xK
xJ
xI
xH
bx G
bx F
bx E
xD
xC
xB
xA
x@
x?
x>
x=
x<
x;
x:
x9
x8
x7
x6
bx 5
bx 4
bx 3
b0 2
x1
x0
0/
bx .
bx -
0,
bx +
bx *
0)
0(
x'
x&
0%
0$
0#
bx "
bx !
$end
#10000
1#
1/
b1 2
#20000
1$
1#
1,
0/
b10 2
#30000
1(
0#
1/
b11 2
#40000
0(
1#
1)
0,
0/
b100 2
#50000
1(
0#
1/
b101 2
#60000
0$
1%
0#
1,
0/
b110 2
#70000
1#
1/
b111 2
#80000
1D
16
0A
17
0>
18
0'
b1000 "
b1000 5
0;
1:
0=
1@
0C
19
1<
0?
0B
00
b101 -
b101 4
b11 *
b11 3
b1000 2
#90000
1'
b0 "
b0 5
0D
1=
0<
1B
b111 -
b111 4
b1001 *
b1001 3
#100000
1D
1>
1A
b1111 "
b1111 5
1;
1C
1<
1?
10
b1111 -
b1111 4
b1111 *
b1111 3
#110000
0`
0J
1]
0K
1Z
0L
1W
0M
1T
0c
0f
0N
0I
0H
0&
b11110 !
b11110 G
0Q
0P
0S
1V
0Y
1\
0_
0b
0e
0O
1R
0U
1X
0[
0^
0a
0d
01
b10100 .
b10100 F
b1010 +
b1010 E
#120000
1f
1H
1L
1I
1Q
0W
1Z
b10011011 !
b10011011 G
0c
1P
1S
1_
0R
1U
0X
1^
1a
b110111 .
b110111 F
b1100100 +
b1100100 E
#130000
0f
0`
0H
0J
1]
1c
0L
0K
0I
0Q
1&
1W
b1011110 !
b1011110 G
1Z
0P
0_
1e
0U
1X
0^
1d
b10010110 .
b10010110 F
b11001000 +
b11001000 E
#140000
1f
1`
1K
1H
1M
1L
1J
1I
1Z
1c
1W
1]
1N
b11111111 !
b11111111 G
1Q
1P
1Y
1_
1b
1O
1R
1U
1[
1^
11
b11111111 .
b11111111 F
b11111111 +
b11111111 E
